[
  {
    "Date": "0008-01-26T00:00:00",
    "Type": "Partial",
    "PartialEclipseBegin": "0008-01-26T16:44:47",
    "AorTEclipseBegin": "0001-01-01T00:00:00",
    "MaximumEclipse": "0008-01-26T17:33:00",
    "AorTEclipseEnd": "0001-01-01T00:00:00",
    "PartialEclipseEnd": "0008-01-26T17:33:00",
    "AorTDuration": "00:00:00",
    "Magnitude": 0.689,
    "Coverage": 0.606
  },
  {
    "Date": "0009-07-10T00:00:00",
    "Type": "Partial",
    "PartialEclipseBegin": "0009-07-10T09:15:31",
    "AorTEclipseBegin": "0001-01-01T00:00:00",
    "MaximumEclipse": "0009-07-10T10:19:52",
    "AorTEclipseEnd": "0001-01-01T00:00:00",
    "PartialEclipseEnd": "0009-07-10T11:28:46",
    "AorTDuration": "00:00:00",
    "Magnitude": 0.569,
    "Coverage": 0.478
  },
  {
    "Date": "0012-11-02T00:00:00",
    "Type": "Partial",
    "PartialEclipseBegin": "0012-11-02T07:07:00",
    "AorTEclipseBegin": "0001-01-01T00:00:00",
    "MaximumEclipse": "0012-11-02T07:15:03",
    "AorTEclipseEnd": "0001-01-01T00:00:00",
    "PartialEclipseEnd": "0012-11-02T08:05:40",
    "AorTDuration": "00:00:00",
    "Magnitude": 0.496,
    "Coverage": 0.39
  },
  {
    "Date": "0013-04-28T00:00:00",
    "Type": "Partial",
    "PartialEclipseBegin": "0013-04-28T11:19:24",
    "AorTEclipseBegin": "0001-01-01T00:00:00",
    "MaximumEclipse": "0013-04-28T12:53:14",
    "AorTEclipseEnd": "0001-01-01T00:00:00",
    "PartialEclipseEnd": "0013-04-28T14:28:32",
    "AorTDuration": "00:00:00",
    "Magnitude": 0.721,
    "Coverage": 0.639
  },
  {
    "Date": "0022-04-19T00:00:00",
    "Type": "Partial",
    "PartialEclipseBegin": "0022-04-19T06:23:53",
    "AorTEclipseBegin": "0001-01-01T00:00:00",
    "MaximumEclipse": "0022-04-19T07:28:22",
    "AorTEclipseEnd": "0001-01-01T00:00:00",
    "PartialEclipseEnd": "0022-04-19T08:40:08",
    "AorTDuration": "00:00:00",
    "Magnitude": 0.72,
    "Coverage": 0.637
  },
  {
    "Date": "0023-04-08T00:00:00",
    "Type": "Partial",
    "PartialEclipseBegin": "0023-04-08T15:07:54",
    "AorTEclipseBegin": "0001-01-01T00:00:00",
    "MaximumEclipse": "0023-04-08T16:15:42",
    "AorTEclipseEnd": "0001-01-01T00:00:00",
    "PartialEclipseEnd": "0023-04-08T17:17:41",
    "AorTDuration": "00:00:00",
    "Magnitude": 0.516,
    "Coverage": 0.408
  },
  {
    "Date": "0024-09-21T00:00:00",
    "Type": "Partial",
    "PartialEclipseBegin": "0024-09-21T06:15:00",
    "AorTEclipseBegin": "0001-01-01T00:00:00",
    "MaximumEclipse": "0024-09-21T06:16:45",
    "AorTEclipseEnd": "0001-01-01T00:00:00",
    "PartialEclipseEnd": "0024-09-21T07:20:30",
    "AorTDuration": "00:00:00",
    "Magnitude": 0.518,
    "Coverage": 0.4
  },
  {
    "Date": "0025-02-16T00:00:00",
    "Type": "Partial",
    "PartialEclipseBegin": "0025-02-16T11:14:07",
    "AorTEclipseBegin": "0001-01-01T00:00:00",
    "MaximumEclipse": "0025-02-16T11:51:42",
    "AorTEclipseEnd": "0001-01-01T00:00:00",
    "PartialEclipseEnd": "0025-02-16T12:29:40",
    "AorTDuration": "00:00:00",
    "Magnitude": 0.12,
    "Coverage": 0.049
  },
  {
    "Date": "0028-07-10T00:00:00",
    "Type": "Partial",
    "PartialEclipseBegin": "0028-07-10T10:27:17",
    "AorTEclipseBegin": "0001-01-01T00:00:00",
    "MaximumEclipse": "0028-07-10T11:07:45",
    "AorTEclipseEnd": "0001-01-01T00:00:00",
    "PartialEclipseEnd": "0028-07-10T11:49:30",
    "AorTDuration": "00:00:00",
    "Magnitude": 0.137,
    "Coverage": 0.06
  },
  {
    "Date": "0035-02-26T00:00:00",
    "Type": "Partial",
    "PartialEclipseBegin": "0035-02-26T09:26:30",
    "AorTEclipseBegin": "0001-01-01T00:00:00",
    "MaximumEclipse": "0035-02-26T10:44:36",
    "AorTEclipseEnd": "0001-01-01T00:00:00",
    "PartialEclipseEnd": "0035-02-26T12:06:31",
    "AorTDuration": "00:00:00",
    "Magnitude": 0.803,
    "Coverage": 0.752
  },
  {
    "Date": "0036-07-11T00:00:00",
    "Type": "Partial",
    "PartialEclipseBegin": "0036-07-11T19:19:12",
    "AorTEclipseBegin": "0001-01-01T00:00:00",
    "MaximumEclipse": "0036-07-11T19:53:20",
    "AorTEclipseEnd": "0001-01-01T00:00:00",
    "PartialEclipseEnd": "0036-07-11T19:59:00",
    "AorTDuration": "00:00:00",
    "Magnitude": 0.307,
    "Coverage": 0.197
  },
  {
    "Date": "0037-07-01T00:00:00",
    "Type": "Partial",
    "PartialEclipseBegin": "0037-07-01T09:46:19",
    "AorTEclipseBegin": "0001-01-01T00:00:00",
    "MaximumEclipse": "0037-07-01T10:59:57",
    "AorTEclipseEnd": "0001-01-01T00:00:00",
    "PartialEclipseEnd": "0037-07-01T12:17:19",
    "AorTDuration": "00:00:00",
    "Magnitude": 0.596,
    "Coverage": 0.507
  },
  {
    "Date": "0038-12-14T00:00:00",
    "Type": "Partial",
    "PartialEclipseBegin": "0038-12-14T11:41:51",
    "AorTEclipseBegin": "0001-01-01T00:00:00",
    "MaximumEclipse": "0038-12-14T13:00:59",
    "AorTEclipseEnd": "0001-01-01T00:00:00",
    "PartialEclipseEnd": "0038-12-14T14:17:38",
    "AorTDuration": "00:00:00",
    "Magnitude": 0.53,
    "Coverage": 0.426
  },
  {
    "Date": "0042-10-02T00:00:00",
    "Type": "Partial",
    "PartialEclipseBegin": "0042-10-02T15:05:09",
    "AorTEclipseBegin": "0001-01-01T00:00:00",
    "MaximumEclipse": "0042-10-02T16:27:42",
    "AorTEclipseEnd": "0001-01-01T00:00:00",
    "PartialEclipseEnd": "0042-10-02T17:40:27",
    "AorTDuration": "00:00:00",
    "Magnitude": 0.598,
    "Coverage": 0.487
  },
  {
    "Date": "0043-09-21T00:00:00",
    "Type": "Partial",
    "PartialEclipseBegin": "0043-09-21T15:51:19",
    "AorTEclipseBegin": "0001-01-01T00:00:00",
    "MaximumEclipse": "0043-09-21T16:30:33",
    "AorTEclipseEnd": "0001-01-01T00:00:00",
    "PartialEclipseEnd": "0043-09-21T17:07:47",
    "AorTDuration": "00:00:00",
    "Magnitude": 0.127,
    "Coverage": 0.052
  },
  {
    "Date": "0044-02-17T00:00:00",
    "Type": "Partial",
    "PartialEclipseBegin": "0044-02-17T07:30:00",
    "AorTEclipseBegin": "0001-01-01T00:00:00",
    "MaximumEclipse": "0044-02-17T07:38:52",
    "AorTEclipseEnd": "0001-01-01T00:00:00",
    "PartialEclipseEnd": "0044-02-17T08:46:43",
    "AorTDuration": "00:00:00",
    "Magnitude": 0.664,
    "Coverage": 0.575
  },
  {
    "Date": "0046-07-21T00:00:00",
    "Type": "Partial",
    "PartialEclipseBegin": "0046-07-21T19:25:21",
    "AorTEclipseBegin": "0001-01-01T00:00:00",
    "MaximumEclipse": "0046-07-21T19:53:00",
    "AorTEclipseEnd": "0001-01-01T00:00:00",
    "PartialEclipseEnd": "0046-07-21T19:53:00",
    "AorTDuration": "00:00:00",
    "Magnitude": 0.575,
    "Coverage": 0.482
  },
  {
    "Date": "0047-12-05T00:00:00",
    "Type": "Total",
    "PartialEclipseBegin": "0047-12-05T09:03:58",
    "AorTEclipseBegin": "0047-12-05T10:16:24",
    "MaximumEclipse": "0047-12-05T10:16:36",
    "AorTEclipseEnd": "0047-12-05T10:16:49",
    "PartialEclipseEnd": "0047-12-05T11:35:59",
    "AorTDuration": "00:00:25",
    "Magnitude": 1.018,
    "Coverage": 1.0
  },
  {
    "Date": "0050-05-09T00:00:00",
    "Type": "Partial",
    "PartialEclipseBegin": "0050-05-09T05:16:00",
    "AorTEclipseBegin": "0001-01-01T00:00:00",
    "MaximumEclipse": "0050-05-09T06:02:30",
    "AorTEclipseEnd": "0001-01-01T00:00:00",
    "PartialEclipseEnd": "0050-05-09T06:56:17",
    "AorTDuration": "00:00:00",
    "Magnitude": 0.607,
    "Coverage": 0.512
  },
  {
    "Date": "0052-09-11T00:00:00",
    "Type": "Partial",
    "PartialEclipseBegin": "0052-09-11T08:56:53",
    "AorTEclipseBegin": "0001-01-01T00:00:00",
    "MaximumEclipse": "0052-09-11T10:16:25",
    "AorTEclipseEnd": "0001-01-01T00:00:00",
    "PartialEclipseEnd": "0052-09-11T11:41:14",
    "AorTDuration": "00:00:00",
    "Magnitude": 0.663,
    "Coverage": 0.57
  },
  {
    "Date": "0055-07-12T00:00:00",
    "Type": "Partial",
    "PartialEclipseBegin": "0055-07-12T19:08:55",
    "AorTEclipseBegin": "0001-01-01T00:00:00",
    "MaximumEclipse": "0055-07-12T19:52:42",
    "AorTEclipseEnd": "0001-01-01T00:00:00",
    "PartialEclipseEnd": "0055-07-12T19:59:00",
    "AorTDuration": "00:00:00",
    "Magnitude": 0.501,
    "Coverage": 0.395
  },
  {
    "Date": "0057-12-14T00:00:00",
    "Type": "Partial",
    "PartialEclipseBegin": "0057-12-14T11:36:03",
    "AorTEclipseBegin": "0001-01-01T00:00:00",
    "MaximumEclipse": "0057-12-14T12:34:20",
    "AorTEclipseEnd": "0001-01-01T00:00:00",
    "PartialEclipseEnd": "0057-12-14T13:32:17",
    "AorTDuration": "00:00:00",
    "Magnitude": 0.313,
    "Coverage": 0.202
  },
  {
    "Date": "0062-02-27T00:00:00",
    "Type": "Partial",
    "PartialEclipseBegin": "0062-02-27T17:10:57",
    "AorTEclipseBegin": "0001-01-01T00:00:00",
    "MaximumEclipse": "0062-02-27T18:09:31",
    "AorTEclipseEnd": "0001-01-01T00:00:00",
    "PartialEclipseEnd": "0062-02-27T18:13:00",
    "AorTDuration": "00:00:00",
    "Magnitude": 0.515,
    "Coverage": 0.405
  },
  {
    "Date": "0063-08-12T00:00:00",
    "Type": "Partial",
    "PartialEclipseBegin": "0063-08-12T08:28:31",
    "AorTEclipseBegin": "0001-01-01T00:00:00",
    "MaximumEclipse": "0063-08-12T09:06:44",
    "AorTEclipseEnd": "0001-01-01T00:00:00",
    "PartialEclipseEnd": "0063-08-12T09:46:44",
    "AorTDuration": "00:00:00",
    "Magnitude": 0.184,
    "Coverage": 0.093
  },
  {
    "Date": "0067-05-31T00:00:00",
    "Type": "Partial",
    "PartialEclipseBegin": "0067-05-31T06:27:44",
    "AorTEclipseBegin": "0001-01-01T00:00:00",
    "MaximumEclipse": "0067-05-31T07:01:49",
    "AorTEclipseEnd": "0001-01-01T00:00:00",
    "PartialEclipseEnd": "0067-05-31T07:37:35",
    "AorTDuration": "00:00:00",
    "Magnitude": 0.14,
    "Coverage": 0.061
  },
  {
    "Date": "0069-10-03T00:00:00",
    "Type": "Partial",
    "PartialEclipseBegin": "0069-10-03T17:23:55",
    "AorTEclipseBegin": "0001-01-01T00:00:00",
    "MaximumEclipse": "0069-10-03T18:06:00",
    "AorTEclipseEnd": "0001-01-01T00:00:00",
    "PartialEclipseEnd": "0069-10-03T18:06:00",
    "AorTDuration": "00:00:00",
    "Magnitude": 0.562,
    "Coverage": 0.447
  },
  {
    "Date": "0072-03-08T00:00:00",
    "Type": "Partial",
    "PartialEclipseBegin": "0072-03-08T08:19:01",
    "AorTEclipseBegin": "0001-01-01T00:00:00",
    "MaximumEclipse": "0072-03-08T08:43:20",
    "AorTEclipseEnd": "0001-01-01T00:00:00",
    "PartialEclipseEnd": "0072-03-08T09:08:10",
    "AorTDuration": "00:00:00",
    "Magnitude": 0.051,
    "Coverage": 0.014
  },
  {
    "Date": "0074-07-12T00:00:00",
    "Type": "Partial",
    "PartialEclipseBegin": "0074-07-12T13:16:26",
    "AorTEclipseBegin": "0001-01-01T00:00:00",
    "MaximumEclipse": "0074-07-12T13:49:04",
    "AorTEclipseEnd": "0001-01-01T00:00:00",
    "PartialEclipseEnd": "0074-07-12T14:20:52",
    "AorTDuration": "00:00:00",
    "Magnitude": 0.069,
    "Coverage": 0.022
  },
  {
    "Date": "0077-05-10T00:00:00",
    "Type": "Partial",
    "PartialEclipseBegin": "0077-05-10T11:18:14",
    "AorTEclipseBegin": "0001-01-01T00:00:00",
    "MaximumEclipse": "0077-05-10T12:46:17",
    "AorTEclipseEnd": "0001-01-01T00:00:00",
    "PartialEclipseEnd": "0077-05-10T14:13:58",
    "AorTDuration": "00:00:00",
    "Magnitude": 0.929,
    "Coverage": 0.916
  },
  {
    "Date": "0082-08-12T00:00:00",
    "Type": "Partial",
    "PartialEclipseBegin": "0082-08-12T08:26:42",
    "AorTEclipseBegin": "0001-01-01T00:00:00",
    "MaximumEclipse": "0082-08-12T09:30:48",
    "AorTEclipseEnd": "0001-01-01T00:00:00",
    "PartialEclipseEnd": "0082-08-12T10:40:29",
    "AorTDuration": "00:00:00",
    "Magnitude": 0.552,
    "Coverage": 0.456
  },
  {
    "Date": "0085-06-10T00:00:00",
    "Type": "Partial",
    "PartialEclipseBegin": "0085-06-10T14:11:20",
    "AorTEclipseBegin": "0001-01-01T00:00:00",
    "MaximumEclipse": "0085-06-10T15:41:47",
    "AorTEclipseEnd": "0001-01-01T00:00:00",
    "PartialEclipseEnd": "0085-06-10T17:01:23",
    "AorTDuration": "00:00:00",
    "Magnitude": 0.764,
    "Coverage": 0.691
  },
  {
    "Date": "0089-03-30T00:00:00",
    "Type": "Partial",
    "PartialEclipseBegin": "0089-03-30T08:28:53",
    "AorTEclipseBegin": "0001-01-01T00:00:00",
    "MaximumEclipse": "0089-03-30T09:36:30",
    "AorTEclipseEnd": "0001-01-01T00:00:00",
    "PartialEclipseEnd": "0089-03-30T10:49:08",
    "AorTDuration": "00:00:00",
    "Magnitude": 0.62,
    "Coverage": 0.529
  },
  {
    "Date": "0090-08-13T00:00:00",
    "Type": "Partial",
    "PartialEclipseBegin": "0090-08-13T18:41:11",
    "AorTEclipseBegin": "0001-01-01T00:00:00",
    "MaximumEclipse": "0090-08-13T19:00:22",
    "AorTEclipseEnd": "0001-01-01T00:00:00",
    "PartialEclipseEnd": "0090-08-13T19:19:15",
    "AorTDuration": "00:00:00",
    "Magnitude": 0.077,
    "Coverage": 0.026
  },
  {
    "Date": "0091-08-03T00:00:00",
    "Type": "Partial",
    "PartialEclipseBegin": "0091-08-03T08:04:50",
    "AorTEclipseBegin": "0001-01-01T00:00:00",
    "MaximumEclipse": "0091-08-03T08:40:39",
    "AorTEclipseEnd": "0001-01-01T00:00:00",
    "PartialEclipseEnd": "0091-08-03T09:18:12",
    "AorTDuration": "00:00:00",
    "Magnitude": 0.135,
    "Coverage": 0.058
  },
  {
    "Date": "0093-01-15T00:00:00",
    "Type": "Partial",
    "PartialEclipseBegin": "0093-01-15T15:04:04",
    "AorTEclipseBegin": "0001-01-01T00:00:00",
    "MaximumEclipse": "0093-01-15T16:14:52",
    "AorTEclipseEnd": "0001-01-01T00:00:00",
    "PartialEclipseEnd": "0093-01-15T17:19:23",
    "AorTDuration": "00:00:00",
    "Magnitude": 0.939,
    "Coverage": 0.926
  },
  {
    "Date": "0096-11-03T00:00:00",
    "Type": "Partial",
    "PartialEclipseBegin": "0096-11-03T14:34:14",
    "AorTEclipseBegin": "0001-01-01T00:00:00",
    "MaximumEclipse": "0096-11-03T15:58:03",
    "AorTEclipseEnd": "0001-01-01T00:00:00",
    "PartialEclipseEnd": "0096-11-03T17:11:22",
    "AorTDuration": "00:00:00",
    "Magnitude": 0.481,
    "Coverage": 0.359
  },
  {
    "Date": "0097-10-23T00:00:00",
    "Type": "Partial",
    "PartialEclipseBegin": "0097-10-23T14:56:59",
    "AorTEclipseBegin": "0001-01-01T00:00:00",
    "MaximumEclipse": "0097-10-23T16:01:34",
    "AorTEclipseEnd": "0001-01-01T00:00:00",
    "PartialEclipseEnd": "0097-10-23T17:00:33",
    "AorTDuration": "00:00:00",
    "Magnitude": 0.328,
    "Coverage": 0.21
  },
  {
    "Date": "0098-03-21T00:00:00",
    "Type": "Partial",
    "PartialEclipseBegin": "0098-03-21T06:35:00",
    "AorTEclipseBegin": "0001-01-01T00:00:00",
    "MaximumEclipse": "0098-03-21T06:52:14",
    "AorTEclipseEnd": "0001-01-01T00:00:00",
    "PartialEclipseEnd": "0098-03-21T07:58:24",
    "AorTDuration": "00:00:00",
    "Magnitude": 0.877,
    "Coverage": 0.836
  },
  {
    "Date": "0100-08-22T00:00:00",
    "Type": "Partial",
    "PartialEclipseBegin": "0100-08-22T18:35:09",
    "AorTEclipseBegin": "0001-01-01T00:00:00",
    "MaximumEclipse": "0100-08-22T19:16:00",
    "AorTEclipseEnd": "0001-01-01T00:00:00",
    "PartialEclipseEnd": "0100-08-22T19:16:00",
    "AorTDuration": "00:00:00",
    "Magnitude": 0.483,
    "Coverage": 0.375
  }
]